lingorm/__init__.py
lingorm/orm.py
lingorm/common/__init__.py
lingorm/common/common_define.py
lingorm/common/file_helper.py
lingorm/drivers/__init__.py
lingorm/drivers/database_config.py
lingorm/drivers/native_query_abstract.py
lingorm/drivers/order_by_abstract.py
lingorm/drivers/query_abstract.py
lingorm/drivers/query_builder_abstract.py
lingorm/drivers/table_query_abstract.py
lingorm/drivers/where_abstract.py
lingorm/drivers/mysql/__init__.py
lingorm/drivers/mysql/column.py
lingorm/drivers/mysql/config.py
lingorm/drivers/mysql/native.py
lingorm/drivers/mysql/native_query.py
lingorm/drivers/mysql/order_by.py
lingorm/drivers/mysql/pymysql_helper.py
lingorm/drivers/mysql/query.py
lingorm/drivers/mysql/query_builder.py
lingorm/drivers/mysql/table_query.py
lingorm/drivers/mysql/where.py
lingorm/drivers/sqlite/__init__.py
lingorm/drivers/sqlite/column.py
lingorm/drivers/sqlite/config.py
lingorm/drivers/sqlite/native.py
lingorm/drivers/sqlite/native_query.py
lingorm/drivers/sqlite/order_by.py
lingorm/drivers/sqlite/query.py
lingorm/drivers/sqlite/query_builder.py
lingorm/drivers/sqlite/table_query.py
lingorm/drivers/sqlite/where.py
lingorm/mapping/__init__.py
lingorm/mapping/condition.py
lingorm/mapping/entity_converter.py
lingorm/mapping/field.py
lingorm/mapping/field_type.py
lingorm/mapping/orm_entity.py
lingorm/tools/__init__.py
lingorm/tools/entity_template.py
lingorm/tools/mysql_entity_generator.py
test/__init__.py
test/run.py
test/test.py
test/entity/__init__.py
test/entity/company_entity.py
test/entity/first_table_entity.py
test/entity/second_table_entity.py
test/mysql/__init__.py
test/mysql/conftest.py
test/mysql/test_database_config.py
test/mysql/test_delete.py
test/mysql/test_insert.py
test/mysql/test_query.py
test/mysql/test_query_builder.py
test/mysql/test_table_query.py
test/mysql/test_transaction.py
test/mysql/test_update.py
tests/__init__.py
tests/conftest.py
tests/test_database_config.py
tests/test_delete.py
tests/test_insert.py
tests/test_query.py
lingorm-0.0.2.dist-info/LICENSE
lingorm-0.0.2.dist-info/METADATA
lingorm-0.0.2.dist-info/WHEEL
lingorm-0.0.2.dist-info/top_level.txt
lingorm-0.0.2.dist-info/RECORD
