Metadata-Version: 2.1
Name: lingorm
Version: 0.0.2
Summary: orm framework for python
Home-page: https://lingorm.com
Author: xiaolingzi
Author-email: xlne@foxmail.com
Maintainer: xiaolingzi
Maintainer-email: xlne@foxmail.com
License: MIT
Project-URL: Documentation, https://lingorm.com
Project-URL: Code, https://github.com/xiaolingzi/lingorm-python
Project-URL: Issue tracker, https://github.com/xiaolingzi/lingorm-python/issues
Platform: UNKNOWN
Requires-Dist: pymysql
